{
    "wallpaper": "/home/bonnee/.config/wpg/wallpapers/chimera-4.jpg",
    "alpha": "85",

    "special": {
        "background": "#221411",
        "foreground": "#fffdfc",
        "cursor": "#fffdfc"
    },
    "colors": {
        "color0": "#221411",
        "color1": "#ac6657",
        "color2": "#a8976d",
        "color3": "#aaa41f",
        "color4": "#2d72a9",
        "color5": "#a89f8e",
        "color6": "#91a8a6",
        "color7": "#c7c4c3",
        "color8": "#432721",
        "color9": "#f07960",
        "color10": "#eccb7b",
        "color11": "#eae11b",
        "color12": "#2c95e9",
        "color13": "#eed4a4",
        "color14": "#a8eee8",
        "color15": "#fffdfc"
    }
}
